{
    "data": {
        "id": 2,
        "empleados": {
            "id": "f1c8785f-d4ee-4639-98ce-1d763be29230",
            "proyecto": {
                "id": "1da1081b-b5c2-40d6-9b9a-c8f783bb4ed7",
                "created_at": "2024-05-19T23:15:11.610877Z",
                "updated_at": "2024-05-19T23:15:11.610877Z",
                "nombre": "b61"
            },
            "cargo": {
                "id": "7e70289b-5020-4bec-9b43-d0fa6bd7afed",
                "created_at": "2024-05-19T23:14:44.393969Z",
                "updated_at": "2024-05-19T23:14:44.393969Z",
                "nombre": "informatico"
            },
            "areadpt": {
                "id": "8ce8a59e-ea7d-4f4c-a6ec-08895971c409",
                "jefe": {
                    "id": "f1c8785f-d4ee-4639-98ce-1d763be29230",
                    "created_at": "2024-05-14T22:33:52.468743Z",
                    "updated_at": "2024-08-17T21:47:50.251627Z",
                    "nip": 1087,
                    "nombre": "Rorber",
                    "apellido_paterno": "Rodríguez",
                    "apellido_materno": "Arcaya",
                    "ci": "78080324903",
                    "sexo": "M",
                    "color_piel": "B",
                    "telefono": "056058955",
                    "ag": null,
                    "no": "9",
                    "calle": "Angostura #",
                    "entre": null,
                    "y": null,
                    "edif": null,
                    "apto": null,
                    "poblado_barrio": null,
                    "nuevo_ingreso": true,
                    "fecha_cc": "2024-05-14",
                    "cpt": false,
                    "fecha_captado": "2024-05-14",
                    "afp": null,
                    "orm": null,
                    "defensa": null,
                    "estado_vivienda": "B",
                    "propietario": false,
                    "vivienda_vinculada": false,
                    "aptoabg": null,
                    "bloque": null,
                    "cuarto": null,
                    "po": null,
                    "ruta": null,
                    "pantry": null,
                    "foto": "",
                    "estado": "SALIDA",
                    "is_active": true,
                    "ne": "52a1bc51-d3cb-47be-8e07-f035d55a2f24",
                    "especialidad": "cc8a1dd1-5c20-4c4d-8986-1154d94fdf8b",
                    "procedencia": "79cd70b9-56b3-42f4-95e8-9fe60302c7ad",
                    "municipio": "c5a385c2-51a1-4b61-bd24-94d90fe73efb",
                    "provincia": "658c4849-18c3-45e1-b4fb-9fae4143a730",
                    "proyecto": "1da1081b-b5c2-40d6-9b9a-c8f783bb4ed7",
                    "areadpt": "8ce8a59e-ea7d-4f4c-a6ec-08895971c409",
                    "cargo": "7e70289b-5020-4bec-9b43-d0fa6bd7afed",
                    "antdd": null,
                    "turno": null,
                    "pase": null,
                    "pantalon": null,
                    "camisa": null,
                    "calzado": null,
                    "ajtvjt": null
                },
                "created_at": "2024-05-19T23:14:34.498810Z",
                "updated_at": "2024-05-19T23:14:34.498810Z",
                "nombre": "Informática"
            },
            "created_at": "2024-05-14T22:33:52.468743Z",
            "updated_at": "2024-08-17T21:47:50.251627Z",
            "nip": 1087,
            "nombre": "Rorber",
            "apellido_paterno": "Rodríguez",
            "apellido_materno": "Arcaya",
            "ci": "78080324903",
            "sexo": "M",
            "color_piel": "B",
            "telefono": "056058955",
            "ag": null,
            "no": "9",
            "calle": "Angostura #",
            "entre": null,
            "y": null,
            "edif": null,
            "apto": null,
            "poblado_barrio": null,
            "nuevo_ingreso": true,
            "fecha_cc": "2024-05-14",
            "cpt": false,
            "fecha_captado": "2024-05-14",
            "afp": null,
            "orm": null,
            "defensa": null,
            "estado_vivienda": "B",
            "propietario": false,
            "vivienda_vinculada": false,
            "aptoabg": null,
            "bloque": null,
            "cuarto": null,
            "po": null,
            "ruta": null,
            "pantry": null,
            "foto": "",
            "estado": "SALIDA",
            "is_active": true,
            "ne": "52a1bc51-d3cb-47be-8e07-f035d55a2f24",
            "especialidad": "cc8a1dd1-5c20-4c4d-8986-1154d94fdf8b",
            "procedencia": "79cd70b9-56b3-42f4-95e8-9fe60302c7ad",
            "municipio": "c5a385c2-51a1-4b61-bd24-94d90fe73efb",
            "provincia": "658c4849-18c3-45e1-b4fb-9fae4143a730",
            "antdd": null,
            "turno": null,
            "pase": null,
            "pantalon": null,
            "camisa": null,
            "calzado": null,
            "ajtvjt": null
        },
        "last_login": "2024-08-18T16:55:45.951206Z",
        "username": "rorber",
        "email": "rorber1978@gmail.com",
        "is_superuser": false,
        "is_staff": false,
        "is_active": true,
        "is_admin": false,
        "date_joined": "2024-05-14T22:34:29.816174Z"
    },
    "status": 200,
    "statusText": "OK",
    "headers": {
        "content-length": "3002",
        "content-type": "application/json"
    },
    "config": {
        "transitional": {
            "silentJSONParsing": true,
            "forcedJSONParsing": true,
            "clarifyTimeoutError": false
        },
        "adapter": [
            "xhr",
            "http",
            "fetch"
        ],
        "transformRequest": [
            null
        ],
        "transformResponse": [
            null
        ],
        "timeout": 0,
        "xsrfCookieName": "XSRF-TOKEN",
        "xsrfHeaderName": "X-XSRF-TOKEN",
        "maxContentLength": -1,
        "maxBodyLength": -1,
        "env": {},
        "headers": {
            "Accept": "application/json, text/plain, */*",
            "Content-Type": "application/json",
            "Authorization": "Bearer eyJhbGciOiJIUzI1NiIsInR5cCI6IkpXVCJ9.eyJ0b2tlbl90eXBlIjoiYWNjZXNzIiwiZXhwIjoxNzI0MDI4OTQ1LCJpYXQiOjE3MjQwMDAxNDUsImp0aSI6ImQyYzc5OTczODNkNzRlOWU4Mjk4YjdmMTJmMGZhNTUwIiwidXNlcl9pZCI6Mn0.oXTy0ez8xY7Bqzpl7eMXxuyC69dbaI6F6TghF5UZjIU"
        },
        "baseURL": "http://127.0.0.1:8000/",
        "withCredentials": true,
        "method": "get",
        "url": "/users/retrieve/2"
    },
    "request": {}
}